simpletyper/__init__.py
simpletyper/app.py
simpletyper/events/__init__.py
simpletyper/events/gamedone.py
simpletyper/events/progress.py
simpletyper/utils/__init__.py
simpletyper/utils/load_words.py
simpletyper/widgets/__init__.py
simpletyper/widgets/hud.py
simpletyper/widgets/text_box.py
simpletyper/words/commonly_misspelled
simpletyper/words/most_common1000
simpletyper/words/top1000
simpletyper/words/top10000
simpletyper/words/top250
simpletyper/words/top2500
simpletyper/words/top25000
simpletyper/words/top500
simpletyper/words/top5000
simpletyper-0.2.2.dist-info/entry_points.txt
simpletyper-0.2.2.dist-info/LICENSE
simpletyper-0.2.2.dist-info/WHEEL
simpletyper-0.2.2.dist-info/METADATA
simpletyper-0.2.2.dist-info/RECORD
